README.md
setup.py
ys_service/__init__.py
ys_service/host.py
ys_service/service_provider.py
ys_service.egg-info/PKG-INFO
ys_service.egg-info/SOURCES.txt
ys_service.egg-info/dependency_links.txt
ys_service.egg-info/requires.txt
ys_service.egg-info/top_level.txt
ys_service/db_service/__init__.py
ys_service/db_service/base_service.py
ys_service/db_service/mongo_service.py
ys_service/db_service/mysql_service.py
ys_service/db_service/redis_service.py
ys_service/db_service/sqlserver_service.py
ys_service/http_service/__init__.py
ys_service/http_service/_http.py
ys_service/http_service/attach_data_service.py
ys_service/http_service/config_center_service.py
ys_service/http_service/context_attach_data_server.py
ys_service/http_service/http_service.py
ys_service/http_service/log_service.py
ys_service/http_service/mq_service.py
ys_service/http_service/realtime_notice_service.py
ys_service/http_service/reservation_service.py
ys_service/http_service/system_service.py
ys_service/http_service/utils.py
ys_service/http_service/web_service_client.py
ys_service/http_service/ys_requests.py
ys_service/queue_service/__init__.py
ys_service/queue_service/action.py
ys_service/queue_service/base_service.py
ys_service/queue_service/block_service.py
ys_service/queue_service/context.py
ys_service/queue_service/queue.py
ys_service/timing_service/__init__.py
ys_service/timing_service/timing_service.py