Metadata-Version: 2.1
Name: ys-service
Version: 1.0.11
Summary: 云上host,python版
Home-page: UNKNOWN
Author: 7913
Author-email: 84328409@qq.com
License: UNKNOWN
Platform: UNKNOWN
Classifier: Programming Language :: Python :: 3
